setup.py
awsprofile/__init__.py
awsprofile/awsprofile.py
awsprofile.egg-info/PKG-INFO
awsprofile.egg-info/SOURCES.txt
awsprofile.egg-info/dependency_links.txt
awsprofile.egg-info/entry_points.txt
awsprofile.egg-info/not-zip-safe
awsprofile.egg-info/top_level.txt