Metadata-Version: 1.0
Name: awsprofile
Version: 0.4
Summary: Easy way to swap aws iam profiles
Home-page: https://github.com/girishpandit88/awsprofile
Author: girishpandit
Author-email: girschol13@gmail.com
License: MIT
Platform: UNKNOWN
